estuary_client/__init__.py
estuary_client/api_client.py
estuary_client/configuration.py
estuary_client/rest.py
estuary_client/api/__init__.py
estuary_client/api/admin_api.py
estuary_client/api/autoretrieve_api.py
estuary_client/api/collections_api.py
estuary_client/api/content_api.py
estuary_client/api/deals_api.py
estuary_client/api/default_api.py
estuary_client/api/metrics_api.py
estuary_client/api/miner_api.py
estuary_client/api/net_api.py
estuary_client/api/pinning_api.py
estuary_client/api/public_api.py
estuary_client/api/user_api.py
estuary_client/models/__init__.py
estuary_client/models/address_address.py
estuary_client/models/api_channel_id_param.py
estuary_client/models/api_claim_msg_response.py
estuary_client/models/api_claim_response.py
estuary_client/models/api_create_collection_body.py
estuary_client/models/api_delete_content_from_collection_body.py
estuary_client/models/api_empty_resp.py
estuary_client/models/api_estimate_deal_body.py
estuary_client/models/api_get_api_keys_resp.py
estuary_client/models/api_miner_resp.py
estuary_client/models/api_public_node_info.py
estuary_client/models/autoretrieve_init_body.py
estuary_client/models/cid_cid.py
estuary_client/models/collections_cid_type.py
estuary_client/models/collections_collection.py
estuary_client/models/collections_collection_list_response.py
estuary_client/models/content_add_body.py
estuary_client/models/miner_claim_miner_body.py
estuary_client/models/miner_miner_chain_info.py
estuary_client/models/miner_miner_set_info_params.py
estuary_client/models/miner_suspend_miner_body.py
estuary_client/models/peering_peering_peer.py
estuary_client/models/types_ipfs_list_pin_status_response.py
estuary_client/models/types_ipfs_pin.py
estuary_client/models/types_ipfs_pin_status_response.py
estuary_client/models/types_pinning_status.py
estuary_client/models/util_content_add_response.py
estuary_client/models/util_content_create_body.py
estuary_client/models/util_content_type.py
estuary_client-1.0.7.dist-info/METADATA
estuary_client-1.0.7.dist-info/WHEEL
estuary_client-1.0.7.dist-info/top_level.txt
estuary_client-1.0.7.dist-info/RECORD
